setup.py
barwex_sshc/__init__.py
barwex_sshc/cipher.py
barwex_sshc/constants.py
barwex_sshc/entry_scripts.py
barwex_sshc/tsvloader.py
barwex_sshc/types.py
barwex_sshc/utils.py
barwex_sshc.egg-info/PKG-INFO
barwex_sshc.egg-info/SOURCES.txt
barwex_sshc.egg-info/dependency_links.txt
barwex_sshc.egg-info/entry_points.txt
barwex_sshc.egg-info/requires.txt
barwex_sshc.egg-info/top_level.txt