Metadata-Version: 2.1
Name: barwex-sshc
Version: 0.5
Requires-Dist: prettytable>=3.11.0
Requires-Dist: pycryptodome>=3.20.0
